    TRYCATCHBLOCK L0 L1 L2 java/lang/Throwable
    TRYCATCHBLOCK L3 L4 L5 java/lang/Throwable
    TRYCATCHBLOCK L3 L4 L6 null
    TRYCATCHBLOCK L7 L8 L9 java/lang/Throwable
    TRYCATCHBLOCK L5 L10 L6 null
   L11
    NEW org/jacoco/core/test/validation/java7/targets/TryWithResourcesTarget$Resource
    DUP
    INVOKESPECIAL org/jacoco/core/test/validation/java7/targets/TryWithResourcesTarget$Resource.<init> ()V
    ASTORE 0
   L12
    ACONST_NULL
    ASTORE 1
   L3
    ALOAD 0
    INVOKESTATIC org/jacoco/core/test/validation/targets/Stubs.nop (Ljava/lang/Object;)V
   L4
    ALOAD 0
    IFNULL L13
   L14
    ALOAD 1
    IFNULL L15
   L0
    ALOAD 0
    INVOKEINTERFACE java/io/Closeable.close ()V (itf)
   L1
    GOTO L13
   L2
    ASTORE 2
   L16
    ALOAD 1
    ALOAD 2
    INVOKEVIRTUAL java/lang/Throwable.addSuppressed (Ljava/lang/Throwable;)V
   L17
    GOTO L13
   L15
    ALOAD 0
    INVOKEINTERFACE java/io/Closeable.close ()V (itf)
    GOTO L13
   L5
    ASTORE 2
   L18
    ALOAD 2
    ASTORE 1
   L19
    ALOAD 2
    ATHROW
   L6
    ASTORE 3
   L10
    ALOAD 0
    IFNULL L20
   L21
    ALOAD 1
    IFNULL L22
   L7
    ALOAD 0
    INVOKEINTERFACE java/io/Closeable.close ()V (itf)
   L8
    GOTO L20
   L9
    ASTORE 4
   L23
    ALOAD 1
    ALOAD 4
    INVOKEVIRTUAL java/lang/Throwable.addSuppressed (Ljava/lang/Throwable;)V
   L24
    GOTO L20
   L22
    ALOAD 0
    INVOKEINTERFACE java/io/Closeable.close ()V (itf)
   L20
    ALOAD 3
    ATHROW
   L13
    RETURN
   L25
    LOCALVARIABLE suppressedExc Ljava/lang/Throwable; L16 L17 2
    LOCALVARIABLE t Ljava/lang/Throwable; L18 L6 2
    LOCALVARIABLE suppressedExc Ljava/lang/Throwable; L23 L24 4
    LOCALVARIABLE r Ljava/io/Closeable; L12 L25 0
    LOCALVARIABLE primaryExc Ljava/lang/Throwable; L3 L25 1
    LINENUMBER 5 L11
    LINENUMBER 6 L12
    LINENUMBER 8 L3
    LINENUMBER 13 L4
    LINENUMBER 14 L14
    LINENUMBER 16 L0
    LINENUMBER 19 L1
    LINENUMBER 17 L2
    LINENUMBER 18 L16
    LINENUMBER 19 L17
    LINENUMBER 21 L15
    LINENUMBER 9 L5
    LINENUMBER 10 L18
    LINENUMBER 11 L19
    LINENUMBER 13 L6
    LINENUMBER 14 L21
    LINENUMBER 16 L7
    LINENUMBER 19 L8
    LINENUMBER 17 L9
    LINENUMBER 18 L23
    LINENUMBER 19 L24
    LINENUMBER 21 L22
    LINENUMBER 25 L13
    MAXSTACK = 2
    MAXLOCALS = 5
