    TRYCATCHBLOCK L0 L1 L2 java/lang/Throwable
    TRYCATCHBLOCK L3 L4 L5 java/lang/Throwable
    TRYCATCHBLOCK L3 L4 L6 null
    TRYCATCHBLOCK L7 L8 L9 java/lang/Throwable
    TRYCATCHBLOCK L5 L10 L6 null
    TRYCATCHBLOCK L11 L12 L13 java/lang/Exception
    TRYCATCHBLOCK L11 L12 L14 null
    TRYCATCHBLOCK L13 L15 L14 null
    TRYCATCHBLOCK L14 L16 L14 null
    TRYCATCHBLOCK L17 L18 L19 java/lang/Throwable
    TRYCATCHBLOCK L11 L20 L21 java/lang/Throwable
    TRYCATCHBLOCK L11 L20 L22 null
    TRYCATCHBLOCK L23 L24 L25 java/lang/Throwable
    TRYCATCHBLOCK L21 L26 L22 null
    TRYCATCHBLOCK L27 L28 L29 java/lang/Throwable
    TRYCATCHBLOCK L30 L31 L32 java/lang/Throwable
    TRYCATCHBLOCK L30 L31 L33 null
    TRYCATCHBLOCK L34 L35 L36 java/lang/Throwable
    TRYCATCHBLOCK L32 L37 L33 null
    TRYCATCHBLOCK L38 L39 L40 java/lang/Exception
    TRYCATCHBLOCK L38 L39 L41 null
    TRYCATCHBLOCK L40 L42 L41 null
    TRYCATCHBLOCK L41 L43 L41 null
    TRYCATCHBLOCK L44 L38 L45 java/lang/Exception
    TRYCATCHBLOCK L46 L47 L48 java/lang/Throwable
    TRYCATCHBLOCK L49 L50 L51 java/lang/Throwable
    TRYCATCHBLOCK L49 L50 L52 null
    TRYCATCHBLOCK L53 L54 L55 java/lang/Throwable
    TRYCATCHBLOCK L51 L56 L52 null
    TRYCATCHBLOCK L57 L58 L59 java/lang/Exception
    TRYCATCHBLOCK L57 L58 L60 null
    TRYCATCHBLOCK L59 L61 L60 null
    TRYCATCHBLOCK L60 L62 L60 null
    TRYCATCHBLOCK L44 L38 L63 null
    TRYCATCHBLOCK L45 L57 L63 null
    TRYCATCHBLOCK L64 L65 L66 java/lang/Throwable
    TRYCATCHBLOCK L67 L68 L69 java/lang/Throwable
    TRYCATCHBLOCK L67 L68 L70 null
    TRYCATCHBLOCK L71 L72 L73 java/lang/Throwable
    TRYCATCHBLOCK L69 L74 L70 null
    TRYCATCHBLOCK L75 L76 L77 java/lang/Exception
    TRYCATCHBLOCK L75 L76 L78 null
    TRYCATCHBLOCK L77 L79 L78 null
    TRYCATCHBLOCK L78 L80 L78 null
    TRYCATCHBLOCK L63 L75 L63 null
   L44
    NEW org/jacoco/core/test/validation/java7/targets/TryWithResourcesTarget$Resource
    DUP
    INVOKESPECIAL org/jacoco/core/test/validation/java7/targets/TryWithResourcesTarget$Resource.<init> ()V
    ASTORE 0
   L81
    ACONST_NULL
    ASTORE 1
   L11
    NEW org/jacoco/core/test/validation/java7/targets/TryWithResourcesTarget$Resource
    DUP
    INVOKESPECIAL org/jacoco/core/test/validation/java7/targets/TryWithResourcesTarget$Resource.<init> ()V
    ASTORE 2
   L82
    ACONST_NULL
    ASTORE 3
   L3
    NEW java/lang/StringBuilder
    DUP
    INVOKESPECIAL java/lang/StringBuilder.<init> ()V
    ALOAD 0
    INVOKEVIRTUAL java/lang/Object.toString ()Ljava/lang/String;
    INVOKEVIRTUAL java/lang/StringBuilder.append (Ljava/lang/String;)Ljava/lang/StringBuilder;
    ALOAD 2
    INVOKEVIRTUAL java/lang/Object.toString ()Ljava/lang/String;
    INVOKEVIRTUAL java/lang/StringBuilder.append (Ljava/lang/String;)Ljava/lang/StringBuilder;
    INVOKEVIRTUAL java/lang/StringBuilder.toString ()Ljava/lang/String;
    INVOKESTATIC org/jacoco/core/test/validation/targets/Stubs.nop (Ljava/lang/Object;)V
   L4
    ALOAD 2
    IFNULL L12
    ALOAD 3
    IFNULL L83
   L0
    ALOAD 2
    INVOKEVIRTUAL org/jacoco/core/test/validation/java7/targets/TryWithResourcesTarget$Resource.close ()V
   L1
    GOTO L12
   L2
    ASTORE 4
   L84
    ALOAD 3
    ALOAD 4
    INVOKEVIRTUAL java/lang/Throwable.addSuppressed (Ljava/lang/Throwable;)V
   L85
    GOTO L12
   L83
    ALOAD 2
    INVOKEVIRTUAL org/jacoco/core/test/validation/java7/targets/TryWithResourcesTarget$Resource.close ()V
    GOTO L12
   L5
    ASTORE 4
    ALOAD 4
    ASTORE 3
    ALOAD 4
    ATHROW
   L6
    ASTORE 5
   L10
    ALOAD 2
    IFNULL L86
    ALOAD 3
    IFNULL L87
   L7
    ALOAD 2
    INVOKEVIRTUAL org/jacoco/core/test/validation/java7/targets/TryWithResourcesTarget$Resource.close ()V
   L8
    GOTO L86
   L9
    ASTORE 6
   L88
    ALOAD 3
    ALOAD 6
    INVOKEVIRTUAL java/lang/Throwable.addSuppressed (Ljava/lang/Throwable;)V
   L89
    GOTO L86
   L87
    ALOAD 2
    INVOKEVIRTUAL org/jacoco/core/test/validation/java7/targets/TryWithResourcesTarget$Resource.close ()V
   L86
    ALOAD 5
    ATHROW
   L12
    INVOKESTATIC org/jacoco/core/test/validation/targets/Stubs.nop ()V
   L90
    GOTO L20
   L13
    ASTORE 2
   L91
    INVOKESTATIC org/jacoco/core/test/validation/targets/Stubs.nop ()V
   L15
    INVOKESTATIC org/jacoco/core/test/validation/targets/Stubs.nop ()V
   L92
    GOTO L20
   L14
    ASTORE 7
   L16
    INVOKESTATIC org/jacoco/core/test/validation/targets/Stubs.nop ()V
    ALOAD 7
    ATHROW
   L20
    ALOAD 0
    IFNULL L38
    ALOAD 1
    IFNULL L93
   L17
    ALOAD 0
    INVOKEVIRTUAL org/jacoco/core/test/validation/java7/targets/TryWithResourcesTarget$Resource.close ()V
   L18
    GOTO L38
   L19
    ASTORE 2
   L94
    ALOAD 1
    ALOAD 2
    INVOKEVIRTUAL java/lang/Throwable.addSuppressed (Ljava/lang/Throwable;)V
   L95
    GOTO L38
   L93
    ALOAD 0
    INVOKEVIRTUAL org/jacoco/core/test/validation/java7/targets/TryWithResourcesTarget$Resource.close ()V
    GOTO L38
   L21
    ASTORE 2
    ALOAD 2
    ASTORE 1
    ALOAD 2
    ATHROW
   L22
    ASTORE 8
   L26
    ALOAD 0
    IFNULL L96
    ALOAD 1
    IFNULL L97
   L23
    ALOAD 0
    INVOKEVIRTUAL org/jacoco/core/test/validation/java7/targets/TryWithResourcesTarget$Resource.close ()V
   L24
    GOTO L96
   L25
    ASTORE 9
   L98
    ALOAD 1
    ALOAD 9
    INVOKEVIRTUAL java/lang/Throwable.addSuppressed (Ljava/lang/Throwable;)V
   L99
    GOTO L96
   L97
    ALOAD 0
    INVOKEVIRTUAL org/jacoco/core/test/validation/java7/targets/TryWithResourcesTarget$Resource.close ()V
   L96
    ALOAD 8
    ATHROW
   L38
    NEW org/jacoco/core/test/validation/java7/targets/TryWithResourcesTarget$Resource
    DUP
    INVOKESPECIAL org/jacoco/core/test/validation/java7/targets/TryWithResourcesTarget$Resource.<init> ()V
    ASTORE 0
   L100
    ACONST_NULL
    ASTORE 1
   L30
    ALOAD 0
    INVOKESTATIC org/jacoco/core/test/validation/targets/Stubs.nop (Ljava/lang/Object;)V
   L31
    ALOAD 0
    IFNULL L39
    ALOAD 1
    IFNULL L101
   L27
    ALOAD 0
    INVOKEVIRTUAL org/jacoco/core/test/validation/java7/targets/TryWithResourcesTarget$Resource.close ()V
   L28
    GOTO L39
   L29
    ASTORE 2
   L102
    ALOAD 1
    ALOAD 2
    INVOKEVIRTUAL java/lang/Throwable.addSuppressed (Ljava/lang/Throwable;)V
   L103
    GOTO L39
   L101
    ALOAD 0
    INVOKEVIRTUAL org/jacoco/core/test/validation/java7/targets/TryWithResourcesTarget$Resource.close ()V
    GOTO L39
   L32
    ASTORE 2
    ALOAD 2
    ASTORE 1
    ALOAD 2
    ATHROW
   L33
    ASTORE 10
   L37
    ALOAD 0
    IFNULL L104
    ALOAD 1
    IFNULL L105
   L34
    ALOAD 0
    INVOKEVIRTUAL org/jacoco/core/test/validation/java7/targets/TryWithResourcesTarget$Resource.close ()V
   L35
    GOTO L104
   L36
    ASTORE 11
   L106
    ALOAD 1
    ALOAD 11
    INVOKEVIRTUAL java/lang/Throwable.addSuppressed (Ljava/lang/Throwable;)V
   L107
    GOTO L104
   L105
    ALOAD 0
    INVOKEVIRTUAL org/jacoco/core/test/validation/java7/targets/TryWithResourcesTarget$Resource.close ()V
   L104
    ALOAD 10
    ATHROW
   L39
    INVOKESTATIC org/jacoco/core/test/validation/targets/Stubs.nop ()V
   L108
    GOTO L109
   L40
    ASTORE 0
   L110
    INVOKESTATIC org/jacoco/core/test/validation/targets/Stubs.nop ()V
   L42
    INVOKESTATIC org/jacoco/core/test/validation/targets/Stubs.nop ()V
   L111
    GOTO L109
   L41
    ASTORE 12
   L43
    INVOKESTATIC org/jacoco/core/test/validation/targets/Stubs.nop ()V
    ALOAD 12
    ATHROW
   L109
    GOTO L112
   L45
    ASTORE 0
   L113
    INVOKESTATIC org/jacoco/core/test/validation/targets/Stubs.nop ()V
   L57
    NEW org/jacoco/core/test/validation/java7/targets/TryWithResourcesTarget$Resource
    DUP
    INVOKESPECIAL org/jacoco/core/test/validation/java7/targets/TryWithResourcesTarget$Resource.<init> ()V
    ASTORE 0
   L114
    ACONST_NULL
    ASTORE 1
   L49
    ALOAD 0
    INVOKESTATIC org/jacoco/core/test/validation/targets/Stubs.nop (Ljava/lang/Object;)V
   L50
    ALOAD 0
    IFNULL L58
    ALOAD 1
    IFNULL L115
   L46
    ALOAD 0
    INVOKEVIRTUAL org/jacoco/core/test/validation/java7/targets/TryWithResourcesTarget$Resource.close ()V
   L47
    GOTO L58
   L48
    ASTORE 2
   L116
    ALOAD 1
    ALOAD 2
    INVOKEVIRTUAL java/lang/Throwable.addSuppressed (Ljava/lang/Throwable;)V
   L117
    GOTO L58
   L115
    ALOAD 0
    INVOKEVIRTUAL org/jacoco/core/test/validation/java7/targets/TryWithResourcesTarget$Resource.close ()V
    GOTO L58
   L51
    ASTORE 2
    ALOAD 2
    ASTORE 1
    ALOAD 2
    ATHROW
   L52
    ASTORE 13
   L56
    ALOAD 0
    IFNULL L118
    ALOAD 1
    IFNULL L119
   L53
    ALOAD 0
    INVOKEVIRTUAL org/jacoco/core/test/validation/java7/targets/TryWithResourcesTarget$Resource.close ()V
   L54
    GOTO L118
   L55
    ASTORE 14
   L120
    ALOAD 1
    ALOAD 14
    INVOKEVIRTUAL java/lang/Throwable.addSuppressed (Ljava/lang/Throwable;)V
   L121
    GOTO L118
   L119
    ALOAD 0
    INVOKEVIRTUAL org/jacoco/core/test/validation/java7/targets/TryWithResourcesTarget$Resource.close ()V
   L118
    ALOAD 13
    ATHROW
   L58
    INVOKESTATIC org/jacoco/core/test/validation/targets/Stubs.nop ()V
   L122
    GOTO L123
   L59
    ASTORE 0
   L124
    INVOKESTATIC org/jacoco/core/test/validation/targets/Stubs.nop ()V
   L61
    INVOKESTATIC org/jacoco/core/test/validation/targets/Stubs.nop ()V
   L125
    GOTO L123
   L60
    ASTORE 15
   L62
    INVOKESTATIC org/jacoco/core/test/validation/targets/Stubs.nop ()V
    ALOAD 15
    ATHROW
   L123
    GOTO L112
   L63
    ASTORE 16
   L75
    NEW org/jacoco/core/test/validation/java7/targets/TryWithResourcesTarget$Resource
    DUP
    INVOKESPECIAL org/jacoco/core/test/validation/java7/targets/TryWithResourcesTarget$Resource.<init> ()V
    ASTORE 17
   L126
    ACONST_NULL
    ASTORE 18
   L67
    ALOAD 17
    INVOKESTATIC org/jacoco/core/test/validation/targets/Stubs.nop (Ljava/lang/Object;)V
   L68
    ALOAD 17
    IFNULL L76
    ALOAD 18
    IFNULL L127
   L64
    ALOAD 17
    INVOKEVIRTUAL org/jacoco/core/test/validation/java7/targets/TryWithResourcesTarget$Resource.close ()V
   L65
    GOTO L76
   L66
    ASTORE 19
   L128
    ALOAD 18
    ALOAD 19
    INVOKEVIRTUAL java/lang/Throwable.addSuppressed (Ljava/lang/Throwable;)V
   L129
    GOTO L76
   L127
    ALOAD 17
    INVOKEVIRTUAL org/jacoco/core/test/validation/java7/targets/TryWithResourcesTarget$Resource.close ()V
    GOTO L76
   L69
    ASTORE 19
    ALOAD 19
    ASTORE 18
    ALOAD 19
    ATHROW
   L70
    ASTORE 20
   L74
    ALOAD 17
    IFNULL L130
    ALOAD 18
    IFNULL L131
   L71
    ALOAD 17
    INVOKEVIRTUAL org/jacoco/core/test/validation/java7/targets/TryWithResourcesTarget$Resource.close ()V
   L72
    GOTO L130
   L73
    ASTORE 21
   L132
    ALOAD 18
    ALOAD 21
    INVOKEVIRTUAL java/lang/Throwable.addSuppressed (Ljava/lang/Throwable;)V
   L133
    GOTO L130
   L131
    ALOAD 17
    INVOKEVIRTUAL org/jacoco/core/test/validation/java7/targets/TryWithResourcesTarget$Resource.close ()V
   L130
    ALOAD 20
    ATHROW
   L76
    INVOKESTATIC org/jacoco/core/test/validation/targets/Stubs.nop ()V
   L134
    GOTO L135
   L77
    ASTORE 17
   L136
    INVOKESTATIC org/jacoco/core/test/validation/targets/Stubs.nop ()V
   L79
    INVOKESTATIC org/jacoco/core/test/validation/targets/Stubs.nop ()V
   L137
    GOTO L135
   L78
    ASTORE 22
   L80
    INVOKESTATIC org/jacoco/core/test/validation/targets/Stubs.nop ()V
    ALOAD 22
    ATHROW
   L135
    ALOAD 16
    ATHROW
   L112
    RETURN
    LOCALVARIABLE x2 Ljava/lang/Throwable; L84 L85 4
    LOCALVARIABLE x2 Ljava/lang/Throwable; L88 L89 6
    LOCALVARIABLE r2 Lorg/jacoco/core/test/validation/java7/targets/TryWithResourcesTarget$Resource; L82 L12 2
    LOCALVARIABLE e Ljava/lang/Exception; L91 L15 2
    LOCALVARIABLE x2 Ljava/lang/Throwable; L94 L95 2
    LOCALVARIABLE x2 Ljava/lang/Throwable; L98 L99 9
    LOCALVARIABLE r1 Lorg/jacoco/core/test/validation/java7/targets/TryWithResourcesTarget$Resource; L81 L38 0
    LOCALVARIABLE x2 Ljava/lang/Throwable; L102 L103 2
    LOCALVARIABLE x2 Ljava/lang/Throwable; L106 L107 11
    LOCALVARIABLE r2 Lorg/jacoco/core/test/validation/java7/targets/TryWithResourcesTarget$Resource; L100 L39 0
    LOCALVARIABLE e Ljava/lang/Exception; L110 L42 0
    LOCALVARIABLE e Ljava/lang/Exception; L113 L57 0
    LOCALVARIABLE x2 Ljava/lang/Throwable; L116 L117 2
    LOCALVARIABLE x2 Ljava/lang/Throwable; L120 L121 14
    LOCALVARIABLE r2 Lorg/jacoco/core/test/validation/java7/targets/TryWithResourcesTarget$Resource; L114 L58 0
    LOCALVARIABLE e Ljava/lang/Exception; L124 L61 0
    LOCALVARIABLE x2 Ljava/lang/Throwable; L128 L129 19
    LOCALVARIABLE x2 Ljava/lang/Throwable; L132 L133 21
    LOCALVARIABLE r2 Lorg/jacoco/core/test/validation/java7/targets/TryWithResourcesTarget$Resource; L126 L76 17
    LOCALVARIABLE e Ljava/lang/Exception; L136 L79 17
    LINENUMBER 6 L44
    LINENUMBER 5 L81
    LINENUMBER 10 L11
    LINENUMBER 9 L82
    LINENUMBER 12 L3
    LINENUMBER 13 L4
    LINENUMBER 9 L5
    LINENUMBER 13 L6
    LINENUMBER 17 L12
    LINENUMBER 18 L90
    LINENUMBER 14 L13
    LINENUMBER 15 L91
    LINENUMBER 17 L15
    LINENUMBER 18 L92
    LINENUMBER 17 L14
    LINENUMBER 20 L20
    LINENUMBER 5 L21
    LINENUMBER 20 L22
    LINENUMBER 26 L38
    LINENUMBER 25 L100
    LINENUMBER 28 L30
    LINENUMBER 29 L31
    LINENUMBER 25 L32
    LINENUMBER 29 L33
    LINENUMBER 33 L39
    LINENUMBER 34 L108
    LINENUMBER 30 L40
    LINENUMBER 31 L110
    LINENUMBER 33 L42
    LINENUMBER 34 L111
    LINENUMBER 33 L41
    LINENUMBER 36 L109
    LINENUMBER 21 L45
    LINENUMBER 22 L113
    LINENUMBER 26 L57
    LINENUMBER 25 L114
    LINENUMBER 28 L49
    LINENUMBER 29 L50
    LINENUMBER 25 L51
    LINENUMBER 29 L52
    LINENUMBER 33 L58
    LINENUMBER 34 L122
    LINENUMBER 30 L59
    LINENUMBER 31 L124
    LINENUMBER 33 L61
    LINENUMBER 34 L125
    LINENUMBER 33 L60
    LINENUMBER 36 L123
    LINENUMBER 25 L63
    LINENUMBER 26 L75
    LINENUMBER 25 L126
    LINENUMBER 28 L67
    LINENUMBER 29 L68
    LINENUMBER 25 L69
    LINENUMBER 29 L70
    LINENUMBER 33 L76
    LINENUMBER 34 L134
    LINENUMBER 30 L77
    LINENUMBER 31 L136
    LINENUMBER 33 L79
    LINENUMBER 34 L137
    LINENUMBER 33 L78
    LINENUMBER 37 L112
    MAXSTACK = 2
    MAXLOCALS = 23
