   L0
    INVOKESTATIC org/jacoco/core/test/validation/java5/targets/ControlStructuresTarget.unconditionalExecution ()V
   L1
    INVOKESTATIC org/jacoco/core/test/validation/java5/targets/ControlStructuresTarget.missedIfBlock ()V
   L2
    INVOKESTATIC org/jacoco/core/test/validation/java5/targets/ControlStructuresTarget.executedIfBlock ()V
   L3
    INVOKESTATIC org/jacoco/core/test/validation/java5/targets/ControlStructuresTarget.missedWhileBlock ()V
   L4
    INVOKESTATIC org/jacoco/core/test/validation/java5/targets/ControlStructuresTarget.alwaysExecutedWhileBlock ()V
   L5
    INVOKESTATIC org/jacoco/core/test/validation/java5/targets/ControlStructuresTarget.executedWhileBlock ()V
   L6
    INVOKESTATIC org/jacoco/core/test/validation/java5/targets/ControlStructuresTarget.executedDoWhileBlock ()V
   L7
    INVOKESTATIC org/jacoco/core/test/validation/java5/targets/ControlStructuresTarget.missedForBlock ()V
   L8
    INVOKESTATIC org/jacoco/core/test/validation/java5/targets/ControlStructuresTarget.executedForBlock ()V
   L9
    INVOKESTATIC org/jacoco/core/test/validation/java5/targets/ControlStructuresTarget.missedForEachBlock ()V
   L10
    INVOKESTATIC org/jacoco/core/test/validation/java5/targets/ControlStructuresTarget.executedForEachBlock ()V
   L11
    INVOKESTATIC org/jacoco/core/test/validation/java5/targets/ControlStructuresTarget.tableSwitchWithHit ()V
   L12
    INVOKESTATIC org/jacoco/core/test/validation/java5/targets/ControlStructuresTarget.continuedTableSwitchWithHit ()V
   L13
    INVOKESTATIC org/jacoco/core/test/validation/java5/targets/ControlStructuresTarget.tableSwitchWithoutHit ()V
   L14
    INVOKESTATIC org/jacoco/core/test/validation/java5/targets/ControlStructuresTarget.lookupSwitchWithHit ()V
   L15
    INVOKESTATIC org/jacoco/core/test/validation/java5/targets/ControlStructuresTarget.continuedLookupSwitchWithHit ()V
   L16
    INVOKESTATIC org/jacoco/core/test/validation/java5/targets/ControlStructuresTarget.lookupSwitchWithoutHit ()V
   L17
    ICONST_0
    INVOKESTATIC org/jacoco/core/test/validation/java5/targets/ControlStructuresTarget.switchImplicitDefaultNotExecuted (I)V
   L18
    ICONST_1
    INVOKESTATIC org/jacoco/core/test/validation/java5/targets/ControlStructuresTarget.switchImplicitDefaultNotExecuted (I)V
   L19
    ICONST_2
    INVOKESTATIC org/jacoco/core/test/validation/java5/targets/ControlStructuresTarget.switchImplicitDefaultNotExecuted (I)V
   L20
    INVOKESTATIC org/jacoco/core/test/validation/java5/targets/ControlStructuresTarget.breakStatement ()V
   L21
    INVOKESTATIC org/jacoco/core/test/validation/java5/targets/ControlStructuresTarget.continueStatement ()V
   L22
    INVOKESTATIC org/jacoco/core/test/validation/java5/targets/ControlStructuresTarget.conditionalReturn ()V
   L23
    INVOKESTATIC org/jacoco/core/test/validation/java5/targets/ControlStructuresTarget.implicitReturn ()V
   L24
    INVOKESTATIC org/jacoco/core/test/validation/java5/targets/ControlStructuresTarget.explicitReturn ()V
   L25
    RETURN
   L26
    LOCALVARIABLE args [Ljava/lang/String; L0 L26 0
    LINENUMBER 5 L0
    LINENUMBER 6 L1
    LINENUMBER 7 L2
    LINENUMBER 8 L3
    LINENUMBER 9 L4
    LINENUMBER 10 L5
    LINENUMBER 11 L6
    LINENUMBER 12 L7
    LINENUMBER 13 L8
    LINENUMBER 14 L9
    LINENUMBER 15 L10
    LINENUMBER 16 L11
    LINENUMBER 17 L12
    LINENUMBER 18 L13
    LINENUMBER 19 L14
    LINENUMBER 20 L15
    LINENUMBER 21 L16
    LINENUMBER 22 L17
    LINENUMBER 23 L18
    LINENUMBER 24 L19
    LINENUMBER 25 L20
    LINENUMBER 26 L21
    LINENUMBER 27 L22
    LINENUMBER 28 L23
    LINENUMBER 29 L24
    LINENUMBER 31 L25
    MAXSTACK = 1
    MAXLOCALS = 1
