doRendezvous
    TRYCATCHBLOCK L28 L29 L30 java/lang/RuntimeException
    TRYCATCHBLOCK L31 L32 L33 java/lang/InterruptedException
    TRYCATCHBLOCK L34 L35 L35 null
    TRYCATCHBLOCK L36 L37 L37 null
    TRYCATCHBLOCK L38 L39 L37 null
    TRYCATCHBLOCK L40 L41 L37 null
   L42
    LINENUMBER 324 L42
    ILOAD 2
    IFEQ L43
   L44
    LINENUMBER 325 L44
    INVOKESTATIC java/lang/System.currentTimeMillis ()J
    LSTORE 5
   L45
    LINENUMBER 326 L45
    ALOAD 0
    GETFIELD edu/oswego/cs/dl/util/concurrent/Rendezvous.entryGate_ : Ledu/oswego/cs/dl/util/concurrent/Semaphore;
    LLOAD 3
    INVOKEVIRTUAL edu/oswego/cs/dl/util/concurrent/Semaphore.attempt (J)Z
    IFNE L46
   L47
    LINENUMBER 327 L47
    NEW edu/oswego/cs/dl/util/concurrent/TimeoutException
    DUP
    LLOAD 3
    INVOKESPECIAL edu/oswego/cs/dl/util/concurrent/TimeoutException.<init> (J)V
    ATHROW
   L43
    LINENUMBER 331 L43
    LCONST_0
    LSTORE 5
   L48
    LINENUMBER 332 L48
    ALOAD 0
    GETFIELD edu/oswego/cs/dl/util/concurrent/Rendezvous.entryGate_ : Ledu/oswego/cs/dl/util/concurrent/Semaphore;
    INVOKEVIRTUAL edu/oswego/cs/dl/util/concurrent/Semaphore.acquire ()V
   L46
    LINENUMBER 335 L46
    ALOAD 0
    ASTORE 7
    ALOAD 7
    MONITORENTER
   L36
    LINENUMBER 337 L36
    ACONST_NULL
    ASTORE 8
   L49
    LINENUMBER 339 L49
    ALOAD 0
    DUP
    GETFIELD edu/oswego/cs/dl/util/concurrent/Rendezvous.entries_ : I
    DUP_X1
    ICONST_1
    IADD
    PUTFIELD edu/oswego/cs/dl/util/concurrent/Rendezvous.entries_ : I
    ISTORE 9
   L50
    LINENUMBER 340 L50
    ALOAD 0
    GETFIELD edu/oswego/cs/dl/util/concurrent/Rendezvous.slots_ : [Ljava/lang/Object;
    ILOAD 9
    ALOAD 1
    AASTORE
   L34
    LINENUMBER 344 L34
    ALOAD 0
    GETFIELD edu/oswego/cs/dl/util/concurrent/Rendezvous.entries_ : I
    ALOAD 0
    GETFIELD edu/oswego/cs/dl/util/concurrent/Rendezvous.parties_ : I
    IF_ICMPNE L51
   L52
    LINENUMBER 346 L52
    ALOAD 0
    ALOAD 0
    GETFIELD edu/oswego/cs/dl/util/concurrent/Rendezvous.entries_ : I
    I2L
    PUTFIELD edu/oswego/cs/dl/util/concurrent/Rendezvous.departures_ : J
   L53
    LINENUMBER 347 L53
    ALOAD 0
    INVOKEVIRTUAL java/lang/Object.notifyAll ()V
   L28
    LINENUMBER 350 L28
    ALOAD 0
    GETFIELD edu/oswego/cs/dl/util/concurrent/Rendezvous.broken_ : Z
    IFNE L29
    ALOAD 0
    GETFIELD edu/oswego/cs/dl/util/concurrent/Rendezvous.rendezvousFunction_ : Ledu/oswego/cs/dl/util/concurrent/Rendezvous$RendezvousFunction;
    IFNULL L29
   L54
    LINENUMBER 351 L54
    ALOAD 0
    GETFIELD edu/oswego/cs/dl/util/concurrent/Rendezvous.rendezvousFunction_ : Ledu/oswego/cs/dl/util/concurrent/Rendezvous$RendezvousFunction;
    ALOAD 0
    GETFIELD edu/oswego/cs/dl/util/concurrent/Rendezvous.slots_ : [Ljava/lang/Object;
    INVOKEINTERFACE edu/oswego/cs/dl/util/concurrent/Rendezvous$RendezvousFunction.rendezvousFunction ([Ljava/lang/Object;)V
   L29
    LINENUMBER 352 L29
    GOTO L55
   L30
    LINENUMBER 354 L30
    ASTORE 10
    ALOAD 0
    ICONST_1
    PUTFIELD edu/oswego/cs/dl/util/concurrent/Rendezvous.broken_ : Z
   L56
    LINENUMBER 355 L56
    GOTO L55
   L57
    LINENUMBER 362 L57
    LCONST_0
    LSTORE 10
   L58
    LINENUMBER 363 L58
    ILOAD 2
    IFEQ L31
   L59
    LINENUMBER 364 L59
    LLOAD 3
    INVOKESTATIC java/lang/System.currentTimeMillis ()J
    LLOAD 5
    LSUB
    LSUB
    LSTORE 10
   L60
    LINENUMBER 365 L60
    LLOAD 10
    LCONST_0
    LCMP
    IFGT L31
   L61
    LINENUMBER 366 L61
    ALOAD 0
    ICONST_1
    PUTFIELD edu/oswego/cs/dl/util/concurrent/Rendezvous.broken_ : Z
   L62
    LINENUMBER 367 L62
    ALOAD 0
    ALOAD 0
    GETFIELD edu/oswego/cs/dl/util/concurrent/Rendezvous.entries_ : I
    I2L
    PUTFIELD edu/oswego/cs/dl/util/concurrent/Rendezvous.departures_ : J
   L63
    LINENUMBER 368 L63
    ALOAD 0
    INVOKEVIRTUAL java/lang/Object.notifyAll ()V
   L64
    LINENUMBER 369 L64
    NEW edu/oswego/cs/dl/util/concurrent/TimeoutException
    DUP
    LLOAD 3
    INVOKESPECIAL edu/oswego/cs/dl/util/concurrent/TimeoutException.<init> (J)V
    ATHROW
   L31
    LINENUMBER 374 L31
    ALOAD 0
    LLOAD 10
    INVOKEVIRTUAL java/lang/Object.wait (J)V
   L32
    LINENUMBER 375 L32
    GOTO L51
   L33
    LINENUMBER 377 L33
    ASTORE 12
    ALOAD 0
    GETFIELD edu/oswego/cs/dl/util/concurrent/Rendezvous.broken_ : Z
    IFNE L65
    ALOAD 0
    GETFIELD edu/oswego/cs/dl/util/concurrent/Rendezvous.departures_ : J
    LCONST_0
    LCMP
    IFLE L66
   L65
    LINENUMBER 378 L65
    INVOKESTATIC java/lang/Thread.currentThread ()Ljava/lang/Thread;
    INVOKEVIRTUAL java/lang/Thread.interrupt ()V
   L67
    LINENUMBER 379 L67
    GOTO L55
   L66
    LINENUMBER 382 L66
    ALOAD 0
    ICONST_1
    PUTFIELD edu/oswego/cs/dl/util/concurrent/Rendezvous.broken_ : Z
   L68
    LINENUMBER 383 L68
    ALOAD 0
    ALOAD 0
    GETFIELD edu/oswego/cs/dl/util/concurrent/Rendezvous.entries_ : I
    I2L
    PUTFIELD edu/oswego/cs/dl/util/concurrent/Rendezvous.departures_ : J
   L69
    LINENUMBER 384 L69
    ALOAD 0
    INVOKEVIRTUAL java/lang/Object.notifyAll ()V
   L70
    LINENUMBER 385 L70
    ALOAD 12
    ATHROW
   L51
    LINENUMBER 361 L51
    ALOAD 0
    GETFIELD edu/oswego/cs/dl/util/concurrent/Rendezvous.broken_ : Z
    IFNE L55
    ALOAD 0
    GETFIELD edu/oswego/cs/dl/util/concurrent/Rendezvous.departures_ : J
    LCONST_1
    LCMP
    IFLT L57
   L55
    LINENUMBER 391 L55
    ACONST_NULL
    GOTO L38
   L71
    GOTO L72
   L35
    LINENUMBER 395 L35
    ASTORE 13
    ACONST_NULL
    GOTO L40
   L73
    ALOAD 13
    ATHROW
   L72
    LINENUMBER 406 L72
    ALOAD 0
    GETFIELD edu/oswego/cs/dl/util/concurrent/Rendezvous.broken_ : Z
    IFEQ L74
   L75
    LINENUMBER 407 L75
    NEW edu/oswego/cs/dl/util/concurrent/BrokenBarrierException
    DUP
    ILOAD 9
    INVOKESPECIAL edu/oswego/cs/dl/util/concurrent/BrokenBarrierException.<init> (I)V
    ATHROW
   L74
    LINENUMBER 409 L74
    ALOAD 8
    ASTORE 10
    ALOAD 7
    MONITOREXIT
    ALOAD 10
    ARETURN
   L37
    LINENUMBER 410 L37
    ASTORE 16
    ALOAD 7
    MONITOREXIT
    ALOAD 16
    ATHROW
   L38
    ASTORE 14
    ALOAD 0
    GETFIELD edu/oswego/cs/dl/util/concurrent/Rendezvous.slots_ : [Ljava/lang/Object;
    ILOAD 9
    AALOAD
    ASTORE 8
   L76
    LINENUMBER 398 L76
    ALOAD 0
    DUP
    GETFIELD edu/oswego/cs/dl/util/concurrent/Rendezvous.departures_ : J
    LCONST_1
    LSUB
    DUP2_X1
    PUTFIELD edu/oswego/cs/dl/util/concurrent/Rendezvous.departures_ : J
    LCONST_0
    LCMP
    IFGT L77
   L78
    LINENUMBER 399 L78
    ICONST_0
    ISTORE 15
    GOTO L79
   L80
    ALOAD 0
    GETFIELD edu/oswego/cs/dl/util/concurrent/Rendezvous.slots_ : [Ljava/lang/Object;
    ILOAD 15
    ACONST_NULL
    AASTORE
    IINC 15 1
   L79
    ILOAD 15
    ALOAD 0
    GETFIELD edu/oswego/cs/dl/util/concurrent/Rendezvous.slots_ : [Ljava/lang/Object;
    ARRAYLENGTH
    IF_ICMPLT L80
   L81
    LINENUMBER 400 L81
    ALOAD 0
    GETFIELD edu/oswego/cs/dl/util/concurrent/Rendezvous.entryGate_ : Ledu/oswego/cs/dl/util/concurrent/Semaphore;
    ALOAD 0
    GETFIELD edu/oswego/cs/dl/util/concurrent/Rendezvous.entries_ : I
    I2L
    INVOKEVIRTUAL edu/oswego/cs/dl/util/concurrent/Semaphore.release (J)V
   L82
    LINENUMBER 401 L82
    ALOAD 0
    ICONST_0
    PUTFIELD edu/oswego/cs/dl/util/concurrent/Rendezvous.entries_ : I
   L77
    GOTO L71
   L39
   L40
    ASTORE 14
    ALOAD 0
    GETFIELD edu/oswego/cs/dl/util/concurrent/Rendezvous.slots_ : [Ljava/lang/Object;
    ILOAD 9
    AALOAD
    ASTORE 8
   L83
    LINENUMBER 398 L83
    ALOAD 0
    DUP
    GETFIELD edu/oswego/cs/dl/util/concurrent/Rendezvous.departures_ : J
    LCONST_1
    LSUB
    DUP2_X1
    PUTFIELD edu/oswego/cs/dl/util/concurrent/Rendezvous.departures_ : J
    LCONST_0
    LCMP
    IFGT L84
   L85
    LINENUMBER 399 L85
    ICONST_0
    ISTORE 15
    GOTO L86
   L87
    ALOAD 0
    GETFIELD edu/oswego/cs/dl/util/concurrent/Rendezvous.slots_ : [Ljava/lang/Object;
    ILOAD 15
    ACONST_NULL
    AASTORE
    IINC 15 1
   L86
    ILOAD 15
    ALOAD 0
    GETFIELD edu/oswego/cs/dl/util/concurrent/Rendezvous.slots_ : [Ljava/lang/Object;
    ARRAYLENGTH
    IF_ICMPLT L87
   L88
    LINENUMBER 400 L88
    ALOAD 0
    GETFIELD edu/oswego/cs/dl/util/concurrent/Rendezvous.entryGate_ : Ledu/oswego/cs/dl/util/concurrent/Semaphore;
    ALOAD 0
    GETFIELD edu/oswego/cs/dl/util/concurrent/Rendezvous.entries_ : I
    I2L
    INVOKEVIRTUAL edu/oswego/cs/dl/util/concurrent/Semaphore.release (J)V
   L89
    LINENUMBER 401 L89
    ALOAD 0
    ICONST_0
    PUTFIELD edu/oswego/cs/dl/util/concurrent/Rendezvous.entries_ : I
   L84
    GOTO L73
   L41
