    TRYCATCHBLOCK L0 L1 L2 java/lang/NullPointerException
    TRYCATCHBLOCK L3 L4 L5 org/jacoco/core/test/validation/targets/Stubs$StubException
    TRYCATCHBLOCK L6 L7 L8 org/jacoco/core/test/validation/targets/Stubs$StubException
    TRYCATCHBLOCK L9 L10 L11 org/jacoco/core/test/validation/targets/Stubs$StubException
    TRYCATCHBLOCK L12 L13 L14 org/jacoco/core/test/validation/targets/Stubs$StubException
   L0
    ACONST_NULL
    INVOKESTATIC org/jacoco/core/test/validation/java5/targets/ExceptionsTarget.implicitNullPointerException ([I)V
   L1
    GOTO L3
   L2
    ASTORE 1
   L3
    INVOKESTATIC org/jacoco/core/test/validation/java5/targets/ExceptionsTarget.implicitException ()V
   L4
    GOTO L6
   L5
    ASTORE 1
   L6
    INVOKESTATIC org/jacoco/core/test/validation/java5/targets/ExceptionsTarget.explicitException ()V
   L7
    GOTO L15
   L8
    ASTORE 1
   L15
    INVOKESTATIC org/jacoco/core/test/validation/java5/targets/ExceptionsTarget.noExceptionTryCatch ()V
   L16
    INVOKESTATIC org/jacoco/core/test/validation/java5/targets/ExceptionsTarget.implicitExceptionTryCatch ()V
   L17
    INVOKESTATIC org/jacoco/core/test/validation/java5/targets/ExceptionsTarget.implicitExceptionTryCatchAfterCondition ()V
   L18
    INVOKESTATIC org/jacoco/core/test/validation/java5/targets/ExceptionsTarget.explicitExceptionTryCatch ()V
   L19
    INVOKESTATIC org/jacoco/core/test/validation/java5/targets/ExceptionsTarget.noExceptionFinally ()V
   L9
    INVOKESTATIC org/jacoco/core/test/validation/java5/targets/ExceptionsTarget.explicitExceptionFinally ()V
   L10
    GOTO L12
   L11
    ASTORE 1
   L12
    INVOKESTATIC org/jacoco/core/test/validation/java5/targets/ExceptionsTarget.implicitExceptionFinally ()V
   L13
    GOTO L20
   L14
    ASTORE 1
   L20
    RETURN
   L21
    LOCALVARIABLE args [Ljava/lang/String; L0 L21 0
    LINENUMBER 5 L0
    LINENUMBER 7 L1
    LINENUMBER 6 L2
    LINENUMBER 9 L3
    LINENUMBER 11 L4
    LINENUMBER 10 L5
    LINENUMBER 13 L6
    LINENUMBER 15 L7
    LINENUMBER 14 L8
    LINENUMBER 16 L15
    LINENUMBER 17 L16
    LINENUMBER 18 L17
    LINENUMBER 19 L18
    LINENUMBER 20 L19
    LINENUMBER 22 L9
    LINENUMBER 24 L10
    LINENUMBER 23 L11
    LINENUMBER 26 L12
    LINENUMBER 28 L13
    LINENUMBER 27 L14
    LINENUMBER 29 L20
    MAXSTACK = 1
    MAXLOCALS = 2
